pyfally/__init__.py
pyfally/api.py
pyfally-0.1.1.dist-info/METADATA
pyfally-0.1.1.dist-info/WHEEL
pyfally-0.1.1.dist-info/top_level.txt
pyfally-0.1.1.dist-info/RECORD
