Metadata-Version: 2.1
Name: pyfally
Version: 0.1.1
Summary: A Python library to shorten your urls
Home-page: https://github.com/HEMMEM97/pyfally.git
Author: Fally
Author-email: hemmem17@gmail.com
Classifier: Programming Language :: Python :: 3
Classifier: License :: OSI Approved :: MIT License
Classifier: Operating System :: OS Independent
Requires-Python: >=3.6
Requires-Dist: requests
